{
    "image_path": "/content/Dataset/train/images/036.jpg",
    "image_size": [
        928,
        1769
    ],
    "info_json_path": "/content/Dataset/train/gdt/036.json",
    "important_words": [
        {
            "words": [
                {
                    "Coordinates": {
                        "xmin": 286,
                        "ymin": 582,
                        "xmax": 680,
                        "ymax": 618
                    },
                    "Text": "14/03/2018 4:06:34PM"
                }
            ],
            "label": "date"
        },
        {
            "words": [
                {
                    "Coordinates": {
                        "xmin": 88,
                        "ymin": 1100,
                        "xmax": 367,
                        "ymax": 1149
                    },
                    "Text": "*TOTAL QTY: 1.00"
                },
                {
                    "Coordinates": {
                        "xmin": 774,
                        "ymin": 1109,
                        "xmax": 858,
                        "ymax": 1143
                    },
                    "Text": "0.90"
                }
            ],
            "label": "total"
        },
        {
            "words": [
                {
                    "Coordinates": {
                        "xmin": 88,
                        "ymin": 1169,
                        "xmax": 542,
                        "ymax": 1211
                    },
                    "Text": "TOTAL INCLUDES GST 0%"
                },
                {
                    "Coordinates": {
                        "xmin": 776,
                        "ymin": 1173,
                        "xmax": 861,
                        "ymax": 1214
                    },
                    "Text": "0.90"
                }
            ],
            "label": "total"
        }
    ],
    "total": [
        {
            "xmin": 88,
            "ymin": 1100,
            "xmax": 858,
            "ymax": 1149
        },
        {
            "xmin": 88,
            "ymin": 1169,
            "xmax": 861,
            "ymax": 1214
        }
    ],
    "date": {
        "xmin": 286,
        "ymin": 582,
        "xmax": 680,
        "ymax": 618
    },
    "roi": {
        "xmin": 77,
        "ymin": 164,
        "xmax": 872,
        "ymax": 1694
    },
    "roi_size": [
        795,
        1530
    ]
}