{
    "image_path": "/content/Dataset/train/images/172.jpg",
    "image_size": [
        935,
        1915
    ],
    "info_json_path": "/content/Dataset/train/gdt/172.json",
    "important_words": [
        {
            "words": [
                {
                    "Coordinates": {
                        "xmin": 37,
                        "ymin": 772,
                        "xmax": 119,
                        "ymax": 809
                    },
                    "Text": "DATE"
                },
                {
                    "Coordinates": {
                        "xmin": 184,
                        "ymin": 773,
                        "xmax": 602,
                        "ymax": 811
                    },
                    "Text": ": 29-09-2017 22:19:53"
                }
            ],
            "label": "date"
        },
        {
            "words": [
                {
                    "Coordinates": {
                        "xmin": 39,
                        "ymin": 1366,
                        "xmax": 532,
                        "ymax": 1407
                    },
                    "Text": "TOTAL (INCLUSIVE OF GST):"
                },
                {
                    "Coordinates": {
                        "xmin": 722,
                        "ymin": 1367,
                        "xmax": 839,
                        "ymax": 1404
                    },
                    "Text": "164.40"
                }
            ],
            "label": "total"
        },
        {
            "words": [
                {
                    "Coordinates": {
                        "xmin": 43,
                        "ymin": 1414,
                        "xmax": 264,
                        "ymax": 1455
                    },
                    "Text": "TOTAL :"
                },
                {
                    "Coordinates": {
                        "xmin": 607,
                        "ymin": 1417,
                        "xmax": 837,
                        "ymax": 1454
                    },
                    "Text": "164.40"
                }
            ],
            "label": "total"
        }
    ],
    "total": [
        {
            "xmin": 39,
            "ymin": 1366,
            "xmax": 839,
            "ymax": 1407
        },
        {
            "xmin": 43,
            "ymin": 1414,
            "xmax": 837,
            "ymax": 1455
        }
    ],
    "date": {
        "xmin": 37,
        "ymin": 772,
        "xmax": 602,
        "ymax": 811
    },
    "roi": {
        "xmin": 25,
        "ymin": 251,
        "xmax": 852,
        "ymax": 1772
    },
    "roi_size": [
        827,
        1521
    ]
}