{
    "image_path": "/content/Dataset/train/images/335.jpg",
    "image_size": [
        791,
        2682
    ],
    "info_json_path": "/content/Dataset/train/gdt/335.json",
    "important_words": [
        {
            "words": [
                {
                    "Coordinates": {
                        "xmin": 276,
                        "ymin": 583,
                        "xmax": 648,
                        "ymax": 608
                    },
                    "Text": "PRINTED: 01/05/2018 6:33:22"
                }
            ],
            "label": "date"
        },
        {
            "words": [
                {
                    "Coordinates": {
                        "xmin": 212,
                        "ymin": 1988,
                        "xmax": 306,
                        "ymax": 2016
                    },
                    "Text": "TOTAL"
                },
                {
                    "Coordinates": {
                        "xmin": 561,
                        "ymin": 1990,
                        "xmax": 673,
                        "ymax": 2019
                    },
                    "Text": "412.92"
                }
            ],
            "label": "total"
        },
        {
            "words": [
                {
                    "Coordinates": {
                        "xmin": 54,
                        "ymin": 2081,
                        "xmax": 369,
                        "ymax": 2116
                    },
                    "Text": "GRAND TOTAL :"
                },
                {
                    "Coordinates": {
                        "xmin": 553,
                        "ymin": 2086,
                        "xmax": 670,
                        "ymax": 2118
                    },
                    "Text": "412.90"
                }
            ],
            "label": "total"
        }
    ],
    "total": [
        {
            "xmin": 212,
            "ymin": 1988,
            "xmax": 673,
            "ymax": 2019
        },
        {
            "xmin": 54,
            "ymin": 2081,
            "xmax": 670,
            "ymax": 2118
        }
    ],
    "date": {
        "xmin": 276,
        "ymin": 583,
        "xmax": 648,
        "ymax": 608
    },
    "roi": {
        "xmin": 43,
        "ymin": 171,
        "xmax": 718,
        "ymax": 2640
    },
    "roi_size": [
        675,
        2469
    ]
}