{
    "image_path": "/content/Dataset/train/images/672.jpg",
    "image_size": [
        620,
        1204
    ],
    "info_json_path": "/content/Dataset/train/gdt/672.json",
    "important_words": [
        {
            "words": [
                {
                    "Coordinates": {
                        "xmin": 324,
                        "ymin": 308,
                        "xmax": 379,
                        "ymax": 327
                    },
                    "Text": "DATE:"
                },
                {
                    "Coordinates": {
                        "xmin": 393,
                        "ymin": 306,
                        "xmax": 513,
                        "ymax": 326
                    },
                    "Text": "30/07/2017"
                }
            ],
            "label": "date"
        },
        {
            "words": [
                {
                    "Coordinates": {
                        "xmin": 236,
                        "ymin": 911,
                        "xmax": 403,
                        "ymax": 952
                    },
                    "Text": "TOTAL PAYABLE:"
                },
                {
                    "Coordinates": {
                        "xmin": 447,
                        "ymin": 913,
                        "xmax": 510,
                        "ymax": 947
                    },
                    "Text": "20.21"
                }
            ],
            "label": "total"
        }
    ],
    "total": [
        {
            "xmin": 236,
            "ymin": 911,
            "xmax": 510,
            "ymax": 952
        }
    ],
    "date": {
        "xmin": 324,
        "ymin": 306,
        "xmax": 513,
        "ymax": 327
    },
    "roi": {
        "xmin": 12,
        "ymin": 54,
        "xmax": 601,
        "ymax": 1184
    },
    "roi_size": [
        589,
        1130
    ]
}