{
    "image_path": "/content/Dataset/train/images/963.jpg",
    "image_size": [
        793,
        1636
    ],
    "info_json_path": "/content/Dataset/train/gdt/963.json",
    "important_words": [
        {
            "words": [
                {
                    "Coordinates": {
                        "xmin": 88,
                        "ymin": 643,
                        "xmax": 152,
                        "ymax": 672
                    },
                    "Text": "DATE"
                },
                {
                    "Coordinates": {
                        "xmin": 194,
                        "ymin": 646,
                        "xmax": 511,
                        "ymax": 674
                    },
                    "Text": ": 20-06-2018 21:36:11"
                }
            ],
            "label": "date"
        },
        {
            "words": [
                {
                    "Coordinates": {
                        "xmin": 87,
                        "ymin": 1086,
                        "xmax": 416,
                        "ymax": 1126
                    },
                    "Text": "TOTAL (EXCLUDING GST):"
                },
                {
                    "Coordinates": {
                        "xmin": 610,
                        "ymin": 1091,
                        "xmax": 695,
                        "ymax": 1127
                    },
                    "Text": "38.00"
                }
            ],
            "label": "total"
        },
        {
            "words": [
                {
                    "Coordinates": {
                        "xmin": 87,
                        "ymin": 1130,
                        "xmax": 466,
                        "ymax": 1163
                    },
                    "Text": "TOTAL (INCLUSIVE OF GST):"
                },
                {
                    "Coordinates": {
                        "xmin": 618,
                        "ymin": 1130,
                        "xmax": 691,
                        "ymax": 1164
                    },
                    "Text": "38.00"
                }
            ],
            "label": "total"
        },
        {
            "words": [
                {
                    "Coordinates": {
                        "xmin": 88,
                        "ymin": 1164,
                        "xmax": 260,
                        "ymax": 1200
                    },
                    "Text": "TOTAL:"
                },
                {
                    "Coordinates": {
                        "xmin": 542,
                        "ymin": 1167,
                        "xmax": 688,
                        "ymax": 1198
                    },
                    "Text": "38.00"
                }
            ],
            "label": "total"
        }
    ],
    "total": [
        {
            "xmin": 87,
            "ymin": 1086,
            "xmax": 695,
            "ymax": 1127
        },
        {
            "xmin": 87,
            "ymin": 1130,
            "xmax": 691,
            "ymax": 1164
        },
        {
            "xmin": 88,
            "ymin": 1164,
            "xmax": 688,
            "ymax": 1200
        }
    ],
    "date": {
        "xmin": 88,
        "ymin": 643,
        "xmax": 511,
        "ymax": 674
    },
    "roi": {
        "xmin": 71,
        "ymin": 321,
        "xmax": 712,
        "ymax": 1626
    },
    "roi_size": [
        641,
        1305
    ]
}